edumated/__init__.py
edumated/__version__.py
edumated/calendar.py
edumated/edumate.py
edumated/edumated.py
edumated/fetch.py
edumated/googcal.py
edumated/util.py
edumated-0.4.2.dist-info/LICENSE
edumated-0.4.2.dist-info/METADATA
edumated-0.4.2.dist-info/WHEEL
edumated-0.4.2.dist-info/entry_points.txt
edumated-0.4.2.dist-info/top_level.txt
edumated-0.4.2.dist-info/RECORD
