Metadata-Version: 2.1
Name: edumated
Version: 0.4.2
Summary: When you've check mated edumate
Home-page: https://github.com/Ninjakow/edumated
Author: Joel Bryla, Daniel O'Connell
Author-email: 
License: UNKNOWN
Platform: UNKNOWN
Classifier: Programming Language :: Python :: 3
Classifier: License :: OSI Approved :: MIT License
Classifier: Operating System :: OS Independent
Requires-Dist: rfc3339
Requires-Dist: google-api-python-client
Requires-Dist: google-auth-httplib2
Requires-Dist: google-auth-oauthlib
Requires-Dist: requests
Requires-Dist: tqdm
Requires-Dist: bs4
